mesh_processing_tools-1.0.4.dist-info/DESCRIPTION.rst
mesh_processing_tools-1.0.4.dist-info/METADATA
mesh_processing_tools-1.0.4.dist-info/RECORD
mesh_processing_tools-1.0.4.dist-info/WHEEL
mesh_processing_tools-1.0.4.dist-info/metadata.json
mesh_processing_tools-1.0.4.dist-info/top_level.txt
mesh_tools/__init__.py
mesh_tools/compartment_utils.py
mesh_tools/meshlab.py
mesh_tools/meshparty_skeletonize.py
mesh_tools/skeleton_utils.py
mesh_tools/trimesh_utils.py
